rellax/__init__.py
rellax/__main__.py
rellax/rellax.py
rellax-0.1rc1.dist-info/LICENSE
rellax-0.1rc1.dist-info/METADATA
rellax-0.1rc1.dist-info/WHEEL
rellax-0.1rc1.dist-info/entry_points.txt
rellax-0.1rc1.dist-info/top_level.txt
rellax-0.1rc1.dist-info/RECORD
