Metadata-Version: 2.1
Name: rellax
Version: 0.1rc1
Summary: Command Line short term knowledgebase management system.
Home-page: UNKNOWN
Author: Jerrad Anderson
Author-email: 
License: UNKNOWN
Platform: UNKNOWN
Requires-Dist: prompt-toolkit (==1.0.15)
Requires-Dist: colored (==1.4.0)
Requires-Dist: inquirer (==2.6.3)
Requires-Dist: tabulate (==0.8.3)
